historicaldate/__init__.py
historicaldate/hdate.py
historicaldate/hdateutils.py
historicaldate-0.1.2.dist-info/LICENSE
historicaldate-0.1.2.dist-info/WHEEL
historicaldate-0.1.2.dist-info/METADATA
historicaldate-0.1.2.dist-info/RECORD
