Metadata-Version: 2.1
Name: historicaldate
Version: 0.1.2
Summary: A small Python package for date handling including support for BC dates and uncertainty
Author-email: David Harris <dharris3968@hotmail.co.uk>
Requires-Python: >=3.8
Classifier: License :: OSI Approved :: MIT License
Project-URL: Documentation, https://historicaldate.readthedocs.io/en/
Project-URL: Home, https://github.com/dh3968mlq/historicaldate
